{
    "type": "report_stats",
    "arena": "Slap Stadium",
    "score": {
        "away": 4,
        "home": 4
    },
    "winner": "none",
    "players": [
        {
            "team": "home",
            "stats": {
                "wins": 1,
                "goals": 1,
                "score": 165,
                "shots": 2,
                "passes": 8,
                "takeaways": 5,
                "faceoffs_won": 1,
                "games_played": 1,
                "faceoffs_lost": 1,
                "conceded_goals": 1,
                "periods_played": 1,
                "contributed_goals": 2,
                "possession_time_sec": 14
            },
            "username": "Crayon",
            "game_user_id": "61597"
        },
        {
            "team": "home",
            "stats": {
                "ties": 1,
                "wins": 1,
                "goals": 2,
                "score": 410,
                "shots": 5,
                "blocks": 1,
                "passes": 14,
                "assists": 1,
                "post_hits": 1,
                "turnovers": 1,
                "games_played": 2,
                "faceoffs_lost": 1,
                "conceded_goals": 4,
                "periods_played": 2,
                "primary_assists": 1,
                "contributed_goals": 4,
                "possession_time_sec": 2
            },
            "username": "Inph1del",
            "game_user_id": "6803"
        },
        {
            "team": "home",
            "stats": {
                "ties": 1,
                "wins": 1,
                "goals": 1,
                "saves": 6,
                "score": 695,
                "shots": 3,
                "blocks": 10,
                "passes": 14,
                "assists": 2,
                "takeaways": 11,
                "turnovers": 2,
                "faceoffs_won": 4,
                "games_played": 2,
                "faceoffs_lost": 1,
                "conceded_goals": 4,
                "periods_played": 2,
                "primary_assists": 2,
                "contributed_goals": 4,
                "possession_time_sec": 83
            },
            "username": "JG Wentworth 877-Cash-Now",
            "game_user_id": "1591253"
        },
        {
            "team": "home",
            "stats": {
                "ties": 1,
                "score": 30,
                "passes": 5,
                "takeaways": 1,
                "faceoffs_won": 2,
                "games_played": 1,
                "conceded_goals": 3,
                "periods_played": 1,
                "contributed_goals": 2,
                "possession_time_sec": 9
            },
            "username": "800-588-2300 Empire Today",
            "game_user_id": "1591250"
        },
        {
            "team": "away",
            "stats": {
                "ties": 1,
                "goals": 2,
                "score": 465,
                "shots": 5,
                "blocks": 5,
                "losses": 1,
                "passes": 16,
                "assists": 1,
                "post_hits": 4,
                "takeaways": 2,
                "turnovers": 8,
                "faceoffs_won": 1,
                "games_played": 2,
                "faceoffs_lost": 4,
                "conceded_goals": 4,
                "periods_played": 2,
                "primary_assists": 1,
                "contributed_goals": 4,
                "possession_time_sec": 7
            },
            "username": "Clever",
            "game_user_id": "1592510"
        },
        {
            "team": "away",
            "stats": {
                "ties": 1,
                "goals": 2,
                "score": 515,
                "shots": 5,
                "blocks": 4,
                "losses": 1,
                "passes": 17,
                "assists": 2,
                "post_hits": 1,
                "takeaways": 1,
                "turnovers": 6,
                "games_played": 2,
                "faceoffs_lost": 1,
                "conceded_goals": 4,
                "periods_played": 2,
                "primary_assists": 2,
                "contributed_goals": 4,
                "possession_time_sec": 20
            },
            "username": "bread",
            "game_user_id": "825118"
        },
        {
            "team": "away",
            "stats": {
                "ties": 1,
                "saves": 6,
                "score": 455,
                "blocks": 9,
                "losses": 1,
                "passes": 8,
                "assists": 2,
                "turnovers": 3,
                "faceoffs_won": 2,
                "games_played": 2,
                "faceoffs_lost": 2,
                "conceded_goals": 4,
                "periods_played": 2,
                "primary_assists": 1,
                "contributed_goals": 4,
                "secondary_assists": 1,
                "possession_time_sec": 26
            },
            "username": "Oblivion",
            "game_user_id": "1071429"
        }
    ],
    "match_id": "4d110e1a-5a2c-4663-b718-2abd5c65cb8e",
    "end_reason": "Tie",
    "match_length": "300",
    "current_period": "2",
    "periods_enabled": "True",
    "custom_mercy_rule": "0"
}