{
    "type": "report_stats",
    "arena": "Slap Stadium",
    "score": {
        "away": 7,
        "home": 12
    },
    "winner": "home",
    "players": [
        {
            "team": "home",
            "stats": {
                "wins": 3,
                "goals": 10,
                "saves": 1,
                "score": 1755,
                "shots": 20,
                "blocks": 5,
                "passes": 37,
                "assists": 2,
                "post_hits": 5,
                "takeaways": 2,
                "turnovers": 2,
                "faceoffs_won": 3,
                "games_played": 2,
                "faceoffs_lost": 2,
                "conceded_goals": 7,
                "periods_played": 3,
                "primary_assists": 1,
                "contributed_goals": 12,
                "secondary_assists": 1,
                "possession_time_sec": 26
            },
            "username": "Jágr",
            "game_user_id": "560316"
        },
        {
            "team": "home",
            "stats": {
                "wins": 3,
                "saves": 3,
                "score": 780,
                "shots": 5,
                "blocks": 2,
                "passes": 31,
                "assists": 6,
                "post_hits": 3,
                "takeaways": 7,
                "turnovers": 2,
                "faceoffs_won": 7,
                "games_played": 2,
                "faceoffs_lost": 3,
                "conceded_goals": 7,
                "periods_played": 3,
                "primary_assists": 5,
                "contributed_goals": 12,
                "secondary_assists": 1,
                "possession_time_sec": 50
            },
            "username": "Kajun",
            "game_user_id": "19508"
        },
        {
            "team": "home",
            "stats": {
                "wins": 3,
                "goals": 2,
                "score": 665,
                "shots": 5,
                "blocks": 2,
                "passes": 26,
                "assists": 4,
                "post_hits": 1,
                "takeaways": 10,
                "turnovers": 1,
                "faceoffs_won": 3,
                "games_played": 2,
                "faceoffs_lost": 3,
                "conceded_goals": 7,
                "periods_played": 3,
                "primary_assists": 3,
                "contributed_goals": 12,
                "secondary_assists": 1,
                "possession_time_sec": 47
            },
            "username": "AboveAverageJoe",
            "game_user_id": "57885"
        },
        {
            "team": "away",
            "stats": {
                "goals": 4,
                "saves": 12,
                "score": 1180,
                "shots": 7,
                "blocks": 8,
                "losses": 3,
                "passes": 15,
                "assists": 1,
                "takeaways": 2,
                "turnovers": 10,
                "faceoffs_won": 2,
                "games_played": 2,
                "faceoffs_lost": 5,
                "conceded_goals": 12,
                "periods_played": 3,
                "primary_assists": 1,
                "contributed_goals": 7,
                "possession_time_sec": 36
            },
            "username": "kevin",
            "game_user_id": "594707"
        },
        {
            "team": "away",
            "stats": {
                "goals": 2,
                "saves": 5,
                "score": 780,
                "shots": 3,
                "blocks": 12,
                "losses": 3,
                "passes": 14,
                "assists": 2,
                "post_hits": 2,
                "takeaways": 2,
                "turnovers": 5,
                "faceoffs_won": 4,
                "games_played": 2,
                "faceoffs_lost": 4,
                "conceded_goals": 12,
                "periods_played": 3,
                "primary_assists": 2,
                "contributed_goals": 7,
                "possession_time_sec": 25
            },
            "username": "Flc",
            "game_user_id": "327512"
        },
        {
            "team": "away",
            "stats": {
                "goals": 1,
                "saves": 1,
                "score": 370,
                "shots": 1,
                "blocks": 3,
                "losses": 3,
                "passes": 20,
                "assists": 2,
                "takeaways": 1,
                "turnovers": 4,
                "faceoffs_won": 2,
                "games_played": 2,
                "faceoffs_lost": 4,
                "conceded_goals": 12,
                "periods_played": 3,
                "primary_assists": 2,
                "contributed_goals": 7,
                "possession_time_sec": 9
            },
            "username": "Poppanut",
            "game_user_id": "191072"
        }
    ],
    "match_id": "0562afdc-5b32-49e6-927a-ddad47342443",
    "end_reason": "EndOfRegulation",
    "match_length": "300",
    "current_period": "3",
    "periods_enabled": "True",
    "custom_mercy_rule": "10"
}