{
  "match": {
    "match_id": "summer_2026_preseason_central_c17",
    "season_id": "summer_2026",
    "season_name": "Summer 2026",
    "phase": "preseason",
    "region": "central",
    "region_display": "Central",
    "division_id": null,
    "division": "Preseason",
    "schedule_id": "C17",
    "home_team_id": "vader_starkillers_central",
    "home_team": "Vader Starkillers Central",
    "away_team_id": "vader_revanites",
    "away_team": "Vader Revanites",
    "status": "final",
    "home_score": 8,
    "away_score": 6,
    "winner_team_id": "vader_starkillers_central",
    "loser_team_id": "vader_revanites",
    "end_reason": "EndOfRegulation",
    "overtime": false,
    "period": 3,
    "thread_id": "1518363784098484305",
    "log_folder": "raw_live_logs/summer_2026/preseason/central/C17_ Vader Starkillers Central vs Vader Revanites__1518363784098484305",
    "report_file": "raw_live_logs/summer_2026/preseason/central/C17_ Vader Starkillers Central vs Vader Revanites__1518363784098484305/20260627_013725_425088453550800906_2026-06-26-21-23-56.json",
    "side_mapping": "normal",
    "side_mapping_confidence": 6,
    "side_mapping_normal_score": 6,
    "side_mapping_swapped_score": 0,
    "warnings": [],
    "side_mapping_roster_source": "active_rosters_fallback"
  },
  "team_stats": {
    "home": {
      "shots": 14,
      "saves": 5,
      "blocks": 15,
      "faceoffs_won": 7,
      "takeaways": 14,
      "possession_time_sec": 78,
      "possession_percent": 38,
      "goals": 8,
      "assists": 5,
      "passes": 56,
      "turnovers": 19,
      "faceoffs_lost": 9,
      "post_hits": 0
    },
    "away": {
      "shots": 11,
      "saves": 6,
      "blocks": 17,
      "faceoffs_won": 9,
      "takeaways": 19,
      "possession_time_sec": 127,
      "possession_percent": 62,
      "goals": 6,
      "assists": 5,
      "passes": 44,
      "turnovers": 14,
      "faceoffs_lost": 7,
      "post_hits": 2
    }
  },
  "players": [
    {
      "team_side": "home",
      "team_id": "vader_starkillers_central",
      "team": "Vader Starkillers Central",
      "slap_id": "524929",
      "username": "Kwispy(ColdHands)",
      "goals": 4,
      "assists": 2,
      "points": 6,
      "shots": 5,
      "saves": 1,
      "blocks": 2,
      "faceoffs_won": 2,
      "faceoffs_lost": 4,
      "takeaways": 5,
      "turnovers": 4,
      "post_hits": 0,
      "passes": 17,
      "possession_time_sec": 28,
      "conceded_goals": 6,
      "shots_faced": 11,
      "save_percent": "0.091",
      "gaa": 6,
      "score": 760
    },
    {
      "team_side": "home",
      "team_id": "vader_starkillers_central",
      "team": "Vader Starkillers Central",
      "slap_id": "524911",
      "username": "Grimace",
      "goals": 2,
      "assists": 2,
      "points": 4,
      "shots": 4,
      "saves": 1,
      "blocks": 5,
      "faceoffs_won": 3,
      "faceoffs_lost": 2,
      "takeaways": 3,
      "turnovers": 5,
      "post_hits": 0,
      "passes": 21,
      "possession_time_sec": 20,
      "conceded_goals": 6,
      "shots_faced": 11,
      "save_percent": "0.091",
      "gaa": 6,
      "score": 580
    },
    {
      "team_side": "home",
      "team_id": "vader_starkillers_central",
      "team": "Vader Starkillers Central",
      "slap_id": "893565",
      "username": "qptreyqp",
      "goals": 2,
      "assists": 1,
      "points": 3,
      "shots": 5,
      "saves": 3,
      "blocks": 8,
      "faceoffs_won": 2,
      "faceoffs_lost": 3,
      "takeaways": 6,
      "turnovers": 10,
      "post_hits": 0,
      "passes": 18,
      "possession_time_sec": 30,
      "conceded_goals": 6,
      "shots_faced": 11,
      "save_percent": "0.273",
      "gaa": 6,
      "score": 615
    },
    {
      "team_side": "away",
      "team_id": "vader_revanites",
      "team": "Vader Revanites",
      "slap_id": "1326629",
      "username": "withdrawals",
      "goals": 4,
      "assists": 2,
      "points": 6,
      "shots": 7,
      "saves": 4,
      "blocks": 10,
      "faceoffs_won": 4,
      "faceoffs_lost": 2,
      "takeaways": 6,
      "turnovers": 6,
      "post_hits": 1,
      "passes": 16,
      "possession_time_sec": 63,
      "conceded_goals": 8,
      "shots_faced": 14,
      "save_percent": "0.286",
      "gaa": 8,
      "score": 1025
    },
    {
      "team_side": "away",
      "team_id": "vader_revanites",
      "team": "Vader Revanites",
      "slap_id": "406789",
      "username": "Sylvatic",
      "goals": 2,
      "assists": 2,
      "points": 4,
      "shots": 3,
      "saves": 2,
      "blocks": 6,
      "faceoffs_won": 4,
      "faceoffs_lost": 2,
      "takeaways": 12,
      "turnovers": 3,
      "post_hits": 1,
      "passes": 14,
      "possession_time_sec": 51,
      "conceded_goals": 8,
      "shots_faced": 14,
      "save_percent": "0.143",
      "gaa": 8,
      "score": 615
    },
    {
      "team_side": "away",
      "team_id": "vader_revanites",
      "team": "Vader Revanites",
      "slap_id": "1362725",
      "username": "x901 Amac",
      "goals": 0,
      "assists": 1,
      "points": 1,
      "shots": 1,
      "saves": 0,
      "blocks": 1,
      "faceoffs_won": 1,
      "faceoffs_lost": 3,
      "takeaways": 1,
      "turnovers": 5,
      "post_hits": 0,
      "passes": 14,
      "possession_time_sec": 13,
      "conceded_goals": 8,
      "shots_faced": 14,
      "save_percent": "0.000",
      "gaa": 8,
      "score": 125
    }
  ],
  "warnings": []
}
