{"type":"report_stats","match_id":"97cebc01-24a0-4476-aeda-90af0e994261","winner":"away","arena":"Slap Stadium","periods_enabled":"True","current_period":"3","custom_mercy_rule":"10","match_length":"300","end_reason":"EndOfRegulation","score":{"home":6,"away":11},"players":[{"game_user_id":"186","team":"home","stats":{"periods_played":3.0,"turnovers":4.0,"conceded_goals":11.0,"faceoffs_lost":4.0,"post_hits":4.0,"passes":28.0,"possession_time_sec":24.0,"shots":6.0,"score":630.0,"assists":4.0,"primary_assists":3.0,"contributed_goals":6.0,"games_played":2.0,"losses":3.0,"takeaways":5.0,"goals":1.0,"faceoffs_won":4.0,"blocks":1.0,"saves":1.0,"secondary_assists":1.0},"username":"Dave."},{"game_user_id":"871020","team":"home","stats":{"periods_played":2.0,"faceoffs_lost":2.0,"conceded_goals":7.0,"blocks":5.0,"score":795.0,"possession_time_sec":21.0,"takeaways":4.0,"goals":4.0,"shots":7.0,"contributed_goals":5.0,"faceoffs_won":4.0,"passes":9.0,"games_played":2.0,"losses":2.0,"assists":1.0,"primary_assists":1.0,"saves":1.0},"username":"X6C-"},{"game_user_id":"1071429","team":"home","stats":{"periods_played":2.0,"blocks":5.0,"score":430.0,"possession_time_sec":64.0,"conceded_goals":7.0,"passes":13.0,"saves":9.0,"takeaways":4.0,"faceoffs_lost":1.0,"assists":1.0,"secondary_assists":1.0,"contributed_goals":3.0,"faceoffs_won":1.0,"games_played":1.0,"losses":2.0},"username":"Oblivion"},{"game_user_id":"914959","team":"home","stats":{"periods_played":3.0,"possession_time_sec":30.0,"conceded_goals":8.0,"takeaways":8.0,"post_hits":1.0,"passes":14.0,"assists":2.0,"primary_assists":2.0,"score":425.0,"contributed_goals":4.0,"shots":3.0,"turnovers":2.0,"faceoffs_won":3.0,"games_played":2.0,"losses":2.0,"goals":1.0,"faceoffs_lost":1.0,"saves":1.0,"blocks":2.0},"username":"Gold"},{"game_user_id":"281017","team":"away","stats":{"periods_played":3.0,"faceoffs_won":5.0,"score":985.0,"passes":26.0,"possession_time_sec":39.0,"takeaways":4.0,"contributed_goals":11.0,"blocks":7.0,"goals":3.0,"shots":8.0,"turnovers":11.0,"conceded_goals":6.0,"games_played":2.0,"wins":3.0,"saves":4.0,"assists":3.0,"secondary_assists":1.0,"faceoffs_lost":2.0,"primary_assists":2.0,"post_hits":1.0},"username":"Looees"},{"game_user_id":"211281","team":"away","stats":{"periods_played":3.0,"possession_time_sec":39.0,"passes":17.0,"contributed_goals":11.0,"takeaways":2.0,"blocks":10.0,"score":525.0,"shots":3.0,"post_hits":1.0,"saves":5.0,"conceded_goals":6.0,"faceoffs_lost":3.0,"games_played":2.0,"wins":3.0,"turnovers":4.0,"assists":1.0,"primary_assists":1.0,"goals":1.0},"username":"doug"},{"game_user_id":"38517","team":"away","stats":{"periods_played":3.0,"passes":27.0,"possession_time_sec":17.0,"goals":7.0,"score":1260.0,"shots":12.0,"contributed_goals":11.0,"takeaways":1.0,"blocks":3.0,"assists":2.0,"primary_assists":2.0,"conceded_goals":6.0,"faceoffs_lost":7.0,"games_played":2.0,"wins":3.0,"faceoffs_won":3.0,"saves":1.0,"turnovers":6.0,"post_hits":2.0},"username":"spectacular333"}]}