{
    "type": "report_stats",
    "arena": "Slap Stadium",
    "score": {
        "away": 7,
        "home": 5
    },
    "winner": "away",
    "players": [
        {
            "team": "home",
            "stats": {
                "wins": 1,
                "goals": 3,
                "score": 485,
                "shots": 4,
                "blocks": 4,
                "losses": 1,
                "passes": 4,
                "takeaways": 4,
                "turnovers": 1,
                "faceoffs_won": 3,
                "games_played": 2,
                "faceoffs_lost": 1,
                "conceded_goals": 7,
                "periods_played": 2,
                "contributed_goals": 5,
                "possession_time_sec": 14
            },
            "username": "JoshAllenfan420",
            "game_user_id": "16435"
        },
        {
            "team": "home",
            "stats": {
                "wins": 1,
                "goals": 2,
                "score": 450,
                "shots": 3,
                "blocks": 1,
                "losses": 1,
                "passes": 11,
                "assists": 2,
                "post_hits": 1,
                "takeaways": 2,
                "turnovers": 1,
                "faceoffs_won": 1,
                "games_played": 2,
                "faceoffs_lost": 4,
                "conceded_goals": 7,
                "periods_played": 2,
                "primary_assists": 2,
                "contributed_goals": 5,
                "possession_time_sec": 6
            },
            "username": "Ol'Woodster",
            "game_user_id": "16437"
        },
        {
            "team": "home",
            "stats": {
                "wins": 1,
                "saves": 5,
                "score": 495,
                "shots": 1,
                "blocks": 4,
                "losses": 1,
                "passes": 6,
                "assists": 3,
                "post_hits": 1,
                "takeaways": 2,
                "faceoffs_won": 2,
                "games_played": 2,
                "faceoffs_lost": 2,
                "conceded_goals": 7,
                "periods_played": 2,
                "primary_assists": 3,
                "contributed_goals": 5,
                "possession_time_sec": 38
            },
            "username": "Jabo",
            "game_user_id": "16422"
        },
        {
            "team": "away",
            "stats": {
                "wins": 1,
                "goals": 5,
                "saves": 1,
                "score": 1015,
                "shots": 6,
                "blocks": 12,
                "losses": 1,
                "passes": 10,
                "assists": 2,
                "post_hits": 3,
                "takeaways": 1,
                "turnovers": 5,
                "faceoffs_won": 4,
                "games_played": 2,
                "faceoffs_lost": 2,
                "conceded_goals": 5,
                "periods_played": 2,
                "primary_assists": 2,
                "contributed_goals": 7,
                "possession_time_sec": 14
            },
            "username": ">:)",
            "game_user_id": "72269"
        },
        {
            "team": "away",
            "stats": {
                "saves": 1,
                "score": 90,
                "shots": 1,
                "losses": 1,
                "passes": 3,
                "takeaways": 1,
                "faceoffs_won": 2,
                "games_played": 1,
                "conceded_goals": 4,
                "periods_played": 1,
                "contributed_goals": 1,
                "possession_time_sec": 20
            },
            "username": "Galalendon",
            "game_user_id": "249493"
        },
        {
            "team": "away",
            "stats": {
                "wins": 1,
                "goals": 2,
                "score": 470,
                "shots": 3,
                "blocks": 3,
                "losses": 1,
                "passes": 9,
                "assists": 2,
                "post_hits": 1,
                "turnovers": 3,
                "faceoffs_won": 1,
                "games_played": 2,
                "faceoffs_lost": 3,
                "conceded_goals": 5,
                "periods_played": 2,
                "primary_assists": 2,
                "contributed_goals": 7,
                "possession_time_sec": 16
            },
            "username": "Ghostwalker",
            "game_user_id": "1439105"
        },
        {
            "team": "away",
            "stats": {
                "wins": 1,
                "saves": 1,
                "score": 210,
                "shots": 2,
                "passes": 3,
                "assists": 2,
                "games_played": 1,
                "faceoffs_lost": 1,
                "conceded_goals": 1,
                "periods_played": 1,
                "primary_assists": 1,
                "contributed_goals": 6,
                "secondary_assists": 1,
                "possession_time_sec": 13
            },
            "username": "Midget",
            "game_user_id": "948283"
        }
    ],
    "match_id": "2a6efe02-b4e6-4a04-b6ad-f68768773da3",
    "end_reason": "EndOfRegulation",
    "match_length": "300",
    "current_period": "2",
    "periods_enabled": "True",
    "custom_mercy_rule": "10"
}