{
    "type": "report_stats",
    "arena": "Slap Stadium",
    "score": {
        "away": 5,
        "home": 6
    },
    "winner": "home",
    "players": [
        {
            "team": "home",
            "stats": {
                "wins": 3,
                "goals": 3,
                "saves": 5,
                "score": 1070,
                "shots": 8,
                "blocks": 14,
                "passes": 47,
                "assists": 3,
                "post_hits": 2,
                "takeaways": 17,
                "turnovers": 1,
                "faceoffs_won": 2,
                "games_played": 2,
                "faceoffs_lost": 1,
                "overtime_wins": 1,
                "conceded_goals": 5,
                "periods_played": 3,
                "primary_assists": 3,
                "contributed_goals": 6,
                "possession_time_sec": 249
            },
            "username": "The Real Teddy Blueger",
            "game_user_id": "848840"
        },
        {
            "team": "home",
            "stats": {
                "wins": 3,
                "goals": 1,
                "score": 360,
                "shots": 1,
                "blocks": 4,
                "passes": 26,
                "assists": 2,
                "takeaways": 2,
                "turnovers": 2,
                "faceoffs_won": 3,
                "games_played": 2,
                "faceoffs_lost": 2,
                "overtime_wins": 1,
                "conceded_goals": 5,
                "periods_played": 3,
                "primary_assists": 2,
                "contributed_goals": 6,
                "possession_time_sec": 12
            },
            "username": "cavitee",
            "game_user_id": "883507"
        },
        {
            "team": "home",
            "stats": {
                "wins": 3,
                "goals": 2,
                "saves": 3,
                "score": 650,
                "shots": 6,
                "blocks": 7,
                "passes": 37,
                "assists": 1,
                "takeaways": 2,
                "turnovers": 1,
                "faceoffs_won": 5,
                "games_played": 2,
                "faceoffs_lost": 1,
                "overtime_wins": 1,
                "conceded_goals": 5,
                "overtime_goals": 1,
                "periods_played": 3,
                "contributed_goals": 6,
                "secondary_assists": 1,
                "game_winning_goals": 1,
                "possession_time_sec": 62
            },
            "username": "Yuvraj",
            "game_user_id": "849146"
        },
        {
            "team": "away",
            "stats": {
                "goals": 1,
                "saves": 4,
                "score": 445,
                "shots": 3,
                "blocks": 8,
                "losses": 2,
                "passes": 13,
                "assists": 1,
                "takeaways": 2,
                "turnovers": 6,
                "games_played": 2,
                "faceoffs_lost": 2,
                "conceded_goals": 4,
                "periods_played": 2,
                "overtime_losses": 1,
                "contributed_goals": 3,
                "secondary_assists": 1,
                "possession_time_sec": 30
            },
            "username": "Nic.",
            "game_user_id": "381872"
        },
        {
            "team": "away",
            "stats": {
                "goals": 1,
                "score": 270,
                "shots": 2,
                "blocks": 3,
                "losses": 2,
                "passes": 11,
                "assists": 1,
                "takeaways": 1,
                "turnovers": 4,
                "faceoffs_won": 1,
                "games_played": 1,
                "faceoffs_lost": 2,
                "conceded_goals": 4,
                "periods_played": 2,
                "primary_assists": 1,
                "contributed_goals": 3,
                "possession_time_sec": 9
            },
            "username": "Trayvon",
            "game_user_id": "56496"
        },
        {
            "team": "away",
            "stats": {
                "goals": 1,
                "saves": 4,
                "score": 555,
                "shots": 4,
                "blocks": 5,
                "losses": 3,
                "passes": 29,
                "assists": 2,
                "post_hits": 1,
                "takeaways": 1,
                "turnovers": 8,
                "faceoffs_won": 1,
                "games_played": 2,
                "faceoffs_lost": 4,
                "conceded_goals": 6,
                "periods_played": 3,
                "overtime_losses": 1,
                "primary_assists": 2,
                "contributed_goals": 5,
                "possession_time_sec": 19
            },
            "username": "bick",
            "game_user_id": "381871"
        },
        {
            "team": "away",
            "stats": {
                "goals": 2,
                "saves": 1,
                "score": 455,
                "shots": 4,
                "blocks": 4,
                "losses": 2,
                "passes": 16,
                "assists": 1,
                "post_hits": 1,
                "turnovers": 3,
                "faceoffs_won": 2,
                "games_played": 2,
                "faceoffs_lost": 2,
                "conceded_goals": 4,
                "periods_played": 2,
                "overtime_losses": 1,
                "contributed_goals": 4,
                "secondary_assists": 1,
                "possession_time_sec": 7
            },
            "username": "diego",
            "game_user_id": "381869"
        }
    ],
    "match_id": "dd4e902c-3253-40aa-bb86-f95a5f6e8b48",
    "end_reason": "Overtime",
    "match_length": "300",
    "current_period": "3",
    "periods_enabled": "True",
    "custom_mercy_rule": "10"
}